version
m3_dl/D.py
m3_dl/__init__.py
m3_dl/__main__.py
m3_dl/m3_dl.py
m3_dl/progress2.py
m3_dl/logx/__init__.py
m3_dl/logx/colored_handler.py
m3_dl/logx/logging.yaml
m3_dl/logx/setup_logging.py
m3_dl-0.0.39.dist-info/METADATA
m3_dl-0.0.39.dist-info/WHEEL
m3_dl-0.0.39.dist-info/entry_points.txt
m3_dl-0.0.39.dist-info/top_level.txt
m3_dl-0.0.39.dist-info/RECORD
