Metadata-Version: 2.1
Name: m3-dl
Version: 0.0.39
Summary: this is a description
Home-page: https://github.com/zk4/m3u8_dl
Author: zk
Author-email: liuzq7@gmail.com
License: BSD
Download-URL: https://github.com/zk4/m3u8_dl/archive/master.zip
Keywords: best practice for python project
Platform: UNKNOWN
Classifier: Development Status :: 5 - Production/Stable
Classifier: Environment :: Console
Requires-Python: >3.7.0
Requires-Dist: urllib3 (==1.25.8)
Requires-Dist: requests (==2.23.0)
Requires-Dist: m3u8 (==0.5.4)
Requires-Dist: termcolor (==1.1.0)
Requires-Dist: pycryptodome (==3.9.8)
Requires-Dist: setuptools (==40.6.3)
Requires-Dist: PyYAML (==5.3.1)
